tsfpga/__init__.py
tsfpga/about.py
tsfpga/build_project_list.py
tsfpga/build_step_tcl_hook.py
tsfpga/constraint.py
tsfpga/create_ghdl_ls_config.py
tsfpga/create_vhdl_ls_config.py
tsfpga/git_simulation_subset.py
tsfpga/git_utils.py
tsfpga/hdl_file.py
tsfpga/ip_core_file.py
tsfpga/math_utils.py
tsfpga/module.py
tsfpga/module_documentation.py
tsfpga/module_list.py
tsfpga/py.typed
tsfpga/requirements.txt
tsfpga/requirements_develop.txt
tsfpga/svn_utils.py
tsfpga/system_utils.py
tsfpga/vhdl_file_documentation.py
tsfpga/examples/__init__.py
tsfpga/examples/build_fpga.py
tsfpga/examples/build_fpga_utils.py
tsfpga/examples/build_module_documentation.py
tsfpga/examples/conf.py
tsfpga/examples/example_env.py
tsfpga/examples/example_pythonpath.py
tsfpga/examples/simulate.py
tsfpga/examples/simulation_utils.py
tsfpga/examples/modules/artyz7/module_artyz7.py
tsfpga/examples/modules/artyz7/regs_artyz7.toml
tsfpga/examples/modules/artyz7/sim/block_design_mock.vhd
tsfpga/examples/modules/artyz7/sim/block_design_mock_pkg.vhd
tsfpga/examples/modules/artyz7/src/artyz7_top.vhd
tsfpga/examples/modules/artyz7/src/artyz7_top_pkg.vhd
tsfpga/examples/modules/artyz7/src/artyz7_top_systemverilog.sv
tsfpga/examples/modules/artyz7/src/artyz7_top_systemverilog_header.svh
tsfpga/examples/modules/artyz7/src/artyz7_top_systemverilog_pkg.sv
tsfpga/examples/modules/artyz7/src/artyz7_top_verilog.v
tsfpga/examples/modules/artyz7/src/artyz7_top_verilog_header.vh
tsfpga/examples/modules/artyz7/src/block_design_pkg.vhd
tsfpga/examples/modules/artyz7/src/block_design_wrapper.vhd
tsfpga/examples/modules/artyz7/src/block_design_wrapper_pkg.vhd
tsfpga/examples/modules/artyz7/src/resync_test.vhd
tsfpga/examples/modules/artyz7/tcl/artyz7_pinning.tcl
tsfpga/examples/modules/artyz7/tcl/block_design.tcl
tsfpga/examples/modules/artyz7/test/tb_artyz7_top.vhd
tsfpga/examples/modules/ddr_buffer/module_ddr_buffer.py
tsfpga/examples/modules/ddr_buffer/regs_ddr_buffer.toml
tsfpga-13.3.0.dist-info/METADATA
tsfpga-13.3.0.dist-info/WHEEL
tsfpga-13.3.0.dist-info/top_level.txt
tsfpga-13.3.0.dist-info/RECORD
