Metadata-Version: 2.4
Name: tsfpga
Version: 13.3.0
Summary: A flexible and scalable development platform for modern FPGA projects
Author: Lukas Vik
Author-email: 10241915+LukasVik@users.noreply.github.com
License: BSD 3-Clause License
Project-URL: Homepage, https://tsfpga.com
Project-URL: Documentation, https://tsfpga.com
Project-URL: Changelog, https://tsfpga.com/release_notes.html
Project-URL: Repository, https://github.com/tsfpga/tsfpga
Project-URL: Issues, https://github.com/tsfpga/tsfpga/issues
Keywords: asic,fpga,ci,simulation,test,vhdl,build-automation,eda,test-automation,rtl,verilog,xilinx,synthesis,vivado,systemverilog,implementation,vunit
Classifier: Development Status :: 5 - Production/Stable
Classifier: Intended Audience :: Developers
Classifier: Intended Audience :: Education
Classifier: Intended Audience :: Information Technology
Classifier: License :: OSI Approved :: BSD License
Classifier: Natural Language :: English
Classifier: Operating System :: MacOS :: MacOS X
Classifier: Operating System :: Microsoft :: Windows
Classifier: Operating System :: OS Independent
Classifier: Operating System :: POSIX :: Linux
Classifier: Topic :: Scientific/Engineering :: Electronic Design Automation (EDA)
Classifier: Topic :: Scientific/Engineering
Classifier: Topic :: Software Development :: Testing
Classifier: Topic :: Software Development
Requires-Python: >=3.9
Requires-Dist: GitPython
Requires-Dist: hdl-registers>=8.0.0
Requires-Dist: rtoml
Requires-Dist: vunit_hdl
Provides-Extra: develop
Requires-Dist: black; extra == "develop"
Requires-Dist: flake8; extra == "develop"
Requires-Dist: GitPython; extra == "develop"
Requires-Dist: packaging; extra == "develop"
Requires-Dist: pybadges; extra == "develop"
Requires-Dist: pylint; extra == "develop"
Requires-Dist: pytest; extra == "develop"
Requires-Dist: pytest-cov; extra == "develop"
Requires-Dist: pytest-xdist; extra == "develop"
Requires-Dist: rtoml; extra == "develop"
Requires-Dist: setuptools; extra == "develop"
Requires-Dist: sphinx; extra == "develop"
Requires-Dist: sphinx_sitemap; extra == "develop"
Requires-Dist: sphinx-rtd-theme; extra == "develop"
Requires-Dist: twine; extra == "develop"
Dynamic: author
Dynamic: author-email
Dynamic: classifier
Dynamic: description
Dynamic: description-content-type
Dynamic: keywords
Dynamic: license
Dynamic: project-url
Dynamic: provides-extra
Dynamic: requires-dist
Dynamic: requires-python
Dynamic: summary
